{
  "url": "https://eecs.berkeley.edu/news/noam-nisan-kimberly-keeton-bruce-hajek-and-nickhil-jakatdar-named-2022-berkeley-eecs",
  "chunks": [
    {
      "chunk_id": 1,
      "text": "Noam Nisan, Kimberly Keeton, Bruce Hajek and Nickhil Jakatdar named 2022 Berkeley EECS Distinguished Alumni - EECS at Berkeley Congratulations to the winners of the 2022 EECS Distinguished Alumni Awards! The CS winners are Noam Nisan (academia) and Kimberly Keeton (industry); and the EE winners are Bruce Hajek (academia) and Nickhil Jakatdar (industry). Noam Nisan (Ph.D. 1988, advisor: Richard Karp), currently a CS professor at Hebrew University of Jerusalem, was cited “For fundamental contributions to computational complexity theory and the creation of the field of algorithmic mechanism design;” Kimberly Keeton (M.S. 1994/Ph.D. 1999, adviser: David Patterson), currently a principal engineer at Google, was cited “For leadership in the research and the production of computer data and storage systems, and for mentoring the next generation of computer scientists and engineers;” Bruce Hajek (Ph.D. 1979, advisor: Eugene Wong), currently an ECE professor at the University of Illinois at Urbana-Champaign, was cited “For his prodigious and fundamental research contributions to stochastic processes, information theory, and communications and computer networks; for his sustained and worldwide influence as a beloved teacher and mentor; and for his major leadership role in electrical and computer engineering;” and Nickhil Jakatdar (Ph.D. 2000, advisor: Costas Spanos), currently the CEO of GenePath Diagnostics, was cited for “For serial entrepreneurship and visionary leadership across several sectors, with profound impact to the microelectronics industry and to the developing world.” Their awards will be presented at the 2022 Berkeley EECS Annual Research Symposium (BEARS) on April 25th. Categories Alumni Honors View Open Faculty"
    },
    {
      "chunk_id": 2,
      "text": "of GenePath Diagnostics, was cited for “For serial entrepreneurship and visionary leadership across several sectors, with profound impact to the microelectronics industry and to the developing world.” Their awards will be presented at the 2022 Berkeley EECS Annual Research Symposium (BEARS) on April 25th. Categories Alumni Honors View Open Faculty Positions"
    }
  ]
}