{
  "url": "https://eecs.berkeley.edu/about/special-events/2022-23",
  "chunks": [
    {
      "chunk_id": 1,
      "text": "2022-23 Archive of Special Events - EECS at Berkeley 2022-23 Archive of Special Events Milestone Dedication for IEEE Standard 754 Join us in celebrating the unveiling of a second IEEE Milestone Plaque, commemorating IEEE Standard 754 for binary floating-point arithmetic, 1985. The ceremony begins Wednesday, May 3rd at 4:00 in Soda Hall, outside the HP auditorium on the third floor, followed by refreshments in the Wozniak Lounge on the fourth floor. Watch the program Berkeley-Stanford Meetup 2023 The 9th Annual Berkeley-Stanford Women in EECS research meetup took place on Saturday, April 29th in the Wozniak Lounge, Soda Hall. The meetup offers all female-identifying, transgender, non-binary, and gender non-conforming graduate students a chance to learn about each other’s research and to network with alums from industry and academia. Read about WiCSE Pravin Varaiya, 1940 - 2022 Celebrating the life of Pravin Varaiya Wednesday, Apr. 19, 2023 | 3:30 PM – 6:00 PM PDT Wozniak Lounge | Soda Hall View photos David Hodges speaking at a 1992 Sproul Association Luncheon while he was dean of engineering. (Photo by Peg Skorpinski) Celebrating the life of Dave Hodges Saturday, Feb. 18, 2023 | 1 p.m. Watch the memorial program BEARS 2023 The Berkeley EECS Annual Research Symposium is an opportunity for everyone in the wider UC Berkeley Electrical Engineering and Computer Sciences community to come together to hear about some of our latest research and celebrate the year’s Distinguished Alumni. This year’s lectures celebrated the department’s 50th anniversary. The program highlighted the wide-reaching impact"
    },
    {
      "chunk_id": 2,
      "text": "Annual Research Symposium is an opportunity for everyone in the wider UC Berkeley Electrical Engineering and Computer Sciences community to come together to hear about some of our latest research and celebrate the year’s Distinguished Alumni. This year’s lectures celebrated the department’s 50th anniversary. The program highlighted the wide-reaching impact of EE+CS at Berkeley in academia and industry over the past five decades. See the 2023 program Support the Gier Memorial Project A community is defined by the heroes it chooses to celebrate. We invite you to join the EECS department in recognizing a previously overlooked hero, Berkeley EE Prof. Joseph T. Gier, the University of California’s first tenured Black professor. Donate Now! About Diversity Undergraduate Diversity Programs $1M Hopper-Dean Foundation Gift for Diversity in CS Presidents of Women in Computer Science and Engineering (WICSE) Diversity Milestones Visiting EECS By the Numbers History Joseph Thomas Gier The First Women of EECS A Relatively Recent History: Women Doctoral Graduates in Electrical Engineering and Computer Sciences, 1969-1981 2025-26 Special Events 2017-18 Archive of Special Events 2018-19 Archive of Special Events 2019-20 Archive of Special Events 2020-21 Archive of Special Events 2022-23 Archive of Special Events 2023-24 Archive of Special Events View Open Faculty Positions"
    }
  ]
}