{
  "url": "http://inst.eecs.berkeley.edu/share/b/pub/ps/labs/105Cory.ps",
  "chunks": [
    {
      "chunk_id": 1,
      "text": "%!PS-Adobe-2.0 %%Title: 105Cory.fig %%Creator: fig2dev Version 3.2 Patchlevel 5 %%CreationDate: Thu Jul 2 13:00:01 2009 %%For: kevinm@ilinux3.EECS.Berkeley.EDU (Kevin_Mullally) %%Orientation: Landscape %%Pages: 2 %%BoundingBox: 0 0 612 792 %%Documen"
    },
    {
      "chunk_id": 2,
      "text": "pe %%Pages: 2 %%BoundingBox: 0 0 612 792 %%DocumentPaperSizes: letter %%BeginSetup [{ %%BeginFeature: *PageRegion Letter < > setpagedevice %%EndFeature } stopped cleartomark %%EndSetup %Magnification: 1.0000 %%EndComments /$F2psDict 200 dict def $F2p"
    },
    {
      "chunk_id": 3,
      "text": "1.0000 %%EndComments /$F2psDict 200 dict def $F2psDict begin $F2psDict /mtrx matrix put /col-1 {0 setgray} bind def /col0 {0.000 0.000 0.000 srgb} bind def /col1 {0.000 0.000 1.000 srgb} bind def /col2 {0.000 1.000 0.000 srgb} bind def /col3 {0.000"
    },
    {
      "chunk_id": 9,
      "text": "rgb} bind def /col27 {1.000 0.500 0.500 srgb} bind def /col28 {1.000 0.630 0.630 srgb} bind def /col29 {1.000 0.750 0.750 srgb} bind def /col30 {1.000 0.880 0.880 srgb} bind def /col31 {1.000 0.840 0.000 srgb} bind def end save newpath 0 792 moveto"
    },
    {
      "chunk_id": 10,
      "text": "000 srgb} bind def end save newpath 0 792 moveto 0 0 lineto 612 0 lineto 612 792 lineto closepath clip newpath -30.6 6.0 translate /cp {closepath} bind def /ef {eofill} bind def /gr {grestore} bind def /gs {gsave} bind def /sa {save} bind def /rs {"
    },
    {
      "chunk_id": 11,
      "text": "def /gs {gsave} bind def /sa {save} bind def /rs {restore} bind def /l {lineto} bind def /m {moveto} bind def /rm {rmoveto} bind def /n {newpath} bind def /s {stroke} bind def /sh {show} bind def /slc {setlinecap} bind def /slj {setlinejoin} bind def"
    },
    {
      "chunk_id": 12,
      "text": "{setlinecap} bind def /slj {setlinejoin} bind def /slw {setlinewidth} bind def /srgb {setrgbcolor} bind def /rot {rotate} bind def /sc {scale} bind def /sd {setdash} bind def /ff {findfont} bind def /sf {setfont} bind def /scf {scalefont} bind def /"
    },
    {
      "chunk_id": 13,
      "text": "/sf {setfont} bind def /scf {scalefont} bind def /sw {stringwidth} bind def /tr {translate} bind def /tnt {dup dup currentrgbcolor 4 -2 roll dup 1 exch sub 3 -1 roll mul add 4 -2 roll dup 1 exch sub 3 -1 roll mul add 4 -2 roll dup 1 exch sub 3"
    },
    {
      "chunk_id": 14,
      "text": "ub 3 -1 roll mul add 4 -2 roll dup 1 exch sub 3 -1 roll mul add srgb} bind def /shd {dup dup currentrgbcolor 4 -2 roll mul 4 -2 roll mul 4 -2 roll mul srgb} bind def /reencdict 12 dict def /ReEncode { reencdict begin /newcodesandnames exch def"
    },
    {
      "chunk_id": 15,
      "text": "code { reencdict begin /newcodesandnames exch def /newfontname exch def /basefontname exch def /basefontdict basefontname findfont def /newfont basefontdict maxlength dict def basefontdict { exch dup /FID ne { dup /Encoding eq { exch dup length array"
    },
    {
      "chunk_id": 16,
      "text": "/FID ne { dup /Encoding eq { exch dup length array copy newfont 3 1 roll put } { exch newfont 3 1 roll put } ifelse } { pop pop } ifelse } forall newfont /FontName newfontname put newcodesandnames aload pop 128 1 255 { newfont /Encoding get exch /.no"
    },
    {
      "chunk_id": 17,
      "text": "ad pop 128 1 255 { newfont /Encoding get exch /.notdef put } for newcodesandnames length 2 idiv { newfont /Encoding get 3 1 roll put } repeat newfontname newfont definefont pop end } def /isovec [ 8#055 /minus 8#200 /grave 8#201 /acute 8#202 /circumf"
    },
    {
      "chunk_id": 18,
      "text": "55 /minus 8#200 /grave 8#201 /acute 8#202 /circumflex 8#203 /tilde 8#204 /macron 8#205 /breve 8#206 /dotaccent 8#207 /dieresis 8#210 /ring 8#211 /cedilla 8#212 /hungarumlaut 8#213 /ogonek 8#214 /caron 8#220 /dotlessi 8#230 /oe 8#231 /OE 8#240 /space"
    },
    {
      "chunk_id": 19,
      "text": "8#220 /dotlessi 8#230 /oe 8#231 /OE 8#240 /space 8#241 /exclamdown 8#242 /cent 8#243 /sterling 8#244 /currency 8#245 /yen 8#246 /brokenbar 8#247 /section 8#250 /dieresis 8#251 /copyright 8#252 /ordfeminine 8#253 /guillemotleft 8#254 /logicalnot 8#25"
    },
    {
      "chunk_id": 20,
      "text": "minine 8#253 /guillemotleft 8#254 /logicalnot 8#255 /hyphen 8#256 /registered 8#257 /macron 8#260 /degree 8#261 /plusminus 8#262 /twosuperior 8#263 /threesuperior 8#264 /acute 8#265 /mu 8#266 /paragraph 8#267 /periodcentered 8#270 /cedilla 8#271 /one"
    },
    {
      "chunk_id": 21,
      "text": "ph 8#267 /periodcentered 8#270 /cedilla 8#271 /onesuperior 8#272 /ordmasculine 8#273 /guillemotright 8#274 /onequarter 8#275 /onehalf 8#276 /threequarters 8#277 /questiondown 8#300 /Agrave 8#301 /Aacute 8#302 /Acircumflex 8#303 /Atilde 8#304 /Adieres"
    },
    {
      "chunk_id": 22,
      "text": "te 8#302 /Acircumflex 8#303 /Atilde 8#304 /Adieresis 8#305 /Aring 8#306 /AE 8#307 /Ccedilla 8#310 /Egrave 8#311 /Eacute 8#312 /Ecircumflex 8#313 /Edieresis 8#314 /Igrave 8#315 /Iacute 8#316 /Icircumflex 8#317 /Idieresis 8#320 /Eth 8#321 /Ntilde 8#322"
    },
    {
      "chunk_id": 23,
      "text": "ex 8#317 /Idieresis 8#320 /Eth 8#321 /Ntilde 8#322 /Ograve 8#323 /Oacute 8#324 /Ocircumflex 8#325 /Otilde 8#326 /Odieresis 8#327 /multiply 8#330 /Oslash 8#331 /Ugrave 8#332 /Uacute 8#333 /Ucircumflex 8#334 /Udieresis 8#335 /Yacute 8#336 /Thorn 8#337"
    },
    {
      "chunk_id": 24,
      "text": "8#334 /Udieresis 8#335 /Yacute 8#336 /Thorn 8#337 /germandbls 8#340 /agrave 8#341 /aacute 8#342 /acircumflex 8#343 /atilde 8#344 /adieresis 8#345 /aring 8#346 /ae 8#347 /ccedilla 8#350 /egrave 8#351 /eacute 8#352 /ecircumflex 8#353 /edieresis 8#354 /"
    },
    {
      "chunk_id": 25,
      "text": "eacute 8#352 /ecircumflex 8#353 /edieresis 8#354 /igrave 8#355 /iacute 8#356 /icircumflex 8#357 /idieresis 8#360 /eth 8#361 /ntilde 8#362 /ograve 8#363 /oacute 8#364 /ocircumflex 8#365 /otilde 8#366 /odieresis 8#367 /divide 8#370 /oslash 8#371 /ugrav"
    },
    {
      "chunk_id": 26,
      "text": "odieresis 8#367 /divide 8#370 /oslash 8#371 /ugrave 8#372 /uacute 8#373 /ucircumflex 8#374 /udieresis 8#375 /yacute 8#376 /thorn 8#377 /ydieresis] def /Times-Roman /Times-Roman-iso isovec ReEncode /$F2psBegin {$F2psDict begin /$F2psEnteredState save"
    },
    {
      "chunk_id": 27,
      "text": "2psBegin {$F2psDict begin /$F2psEnteredState save def} def /$F2psEnd {$F2psEnteredState restore end} def $F2psBegin 10 setmiterlimit 0 slj 0 slc 0.06000 0.06000 sc %%Page: 1 1 %%BeginPageSetup 90 rotate 1 -1 scale %%EndPageSetup % % Fig objects fo"
    },
    {
      "chunk_id": 28,
      "text": "otate 1 -1 scale %%EndPageSetup % % Fig objects follow % % % here starts figure with depth 100 % Polyline 0 slj 0 slc 7.500 slw n 1275 8550 m 2250 8550 l 2250 9300 l 1275 9300 l cp gs col7 0.50 shd ef gr gs col0 s gr % Polyline n 2250 9300 m 3225"
    },
    {
      "chunk_id": 29,
      "text": "ef gr gs col0 s gr % Polyline n 2250 9300 m 3225 9300 l 3225 8925 l 2250 8925 l cp gs col7 0.50 shd ef gr gs col0 s gr % here ends figure; % % here starts figure with depth 50 /Times-Roman-iso ff 166.67 scf sf 1950 2325 m gs 1 -1 sc (Needs an ADA"
    },
    {
      "chunk_id": 38,
      "text": "repeat 11700 3450 11212 3450 37 arcto 4 {pop} repeat cp gs col0 s gr /Times-Roman-iso ff 200.00 scf sf 1500 8978 m gs 1 -1 sc (cabinet) col0 sh gr /Times-Roman-iso ff 200.00 scf sf 2475 9150 m gs 1 -1 sc (cabinet) col0 sh gr % Polyline n 7905 540"
    },
    {
      "chunk_id": 140,
      "text": "0 s gr /Times-Roman-iso ff 166.67 scf sf 9825 6375 m gs 1 -1 sc (overhead projector) col0 sh gr /Times-Roman-iso ff 200.00 scf sf 6699 8130 m gs 1 -1 sc (6') col0 sh gr % here ends figure; % % here starts figure with depth 0 % Polyline 0 slj 0 slc"
    },
    {
      "chunk_id": 143,
      "text": "olyline 7.500 slw n 1950 1875 m 2175 1875 l 2175 1950 l 1950 1950 l cp gs col7 0.50 shd ef gr gs col-1 s gr /Times-Roman-iso ff 166.67 scf sf 2325 1950 m gs 1 -1 sc (= network connections \\(white box on wall\\)) col-1 sh gr /Times-Roman-iso ff 333.3"
    },
    {
      "chunk_id": 144,
      "text": "x on wall\\)) col-1 sh gr /Times-Roman-iso ff 333.33 scf sf 1950 1500 m gs 1 -1 sc (105 Cory Hall) col-1 sh gr /Times-Roman-iso ff 333.33 scf sf 1950 1755 m gs 1 -1 sc (30 PCs) col-1 sh gr /Times-Roman-iso ff 200.00 scf sf 9525 1725 m gs 1 -1 sc (kevi"
    },
    {
      "chunk_id": 145,
      "text": "-iso ff 200.00 scf sf 9525 1725 m gs 1 -1 sc (kevinm@eecs.berkeley.edu) col-1 sh gr /Times-Roman-iso ff 200.00 scf sf 9525 1275 m gs 1 -1 sc (scale: .25\" = 12\" \\(1 in = 4 ft\\)) col-1 sh gr /Times-Roman-iso ff 200.00 scf sf 9525 1500 m gs 1 -1 sc (Ke"
    },
    {
      "chunk_id": 148,
      "text": "n-iso ff 133.33 scf sf 10650 9000 m gs 1 -1 sc 90.0 rot (PC) col-1 sh gr /Times-Roman-iso ff 166.67 scf sf 9675 2700 m gs 1 -1 sc (electrical) col-1 sh gr /Times-Roman-iso ff 166.67 scf sf 9675 2850 m gs 1 -1 sc (panel) col-1 sh gr /Times-Roman-iso"
    },
    {
      "chunk_id": 149,
      "text": "m gs 1 -1 sc (panel) col-1 sh gr /Times-Roman-iso ff 133.33 scf sf 8400 4800 m gs 1 -1 sc 270.0 rot (PC) col-1 sh gr /Times-Roman-iso ff 133.33 scf sf 8625 4800 m gs 1 -1 sc 270.0 rot (PC) col-1 sh gr % Polyline n 9450 5325 m 9450 4575 l 7650 4575"
    },
    {
      "chunk_id": 166,
      "text": "l 7650 8175 l cp gs col-1 s gr /Times-Roman-iso ff 133.33 scf sf 6900 7800 m gs 1 -1 sc 90.0 rot (PC) col-1 sh gr /Times-Roman-iso ff 133.33 scf sf 6675 7800 m gs 1 -1 sc 90.0 rot (PC) col-1 sh gr % Polyline n 5850 8175 m 5850 7425 l 4050 7425 l"
    },
    {
      "chunk_id": 172,
      "text": "l cp gs col7 0.50 shd ef gr gs col-1 s gr % Polyline n 9675 3075 m 10200 3075 l 10200 3000 l 9675 3000 l cp gs col7 0.50 shd ef gr gs col-1 s gr /Times-Roman-iso ff 166.67 scf sf 4875 2850 m gs 1 -1 sc (window) col-1 sh gr /Times-Roman-iso ff 16"
    },
    {
      "chunk_id": 173,
      "text": "-1 sc (window) col-1 sh gr /Times-Roman-iso ff 166.67 scf sf 11175 10050 m gs 1 -1 sc (/usr/pub/xfig/199Cory.fig) col-1 sh gr /Times-Roman-iso ff 166.67 scf sf 525 4950 m gs 1 -1 sc 270.0 rot (foyer) col-1 sh gr /Times-Roman-iso ff 166.67 scf sf 13"
    },
    {
      "chunk_id": 174,
      "text": ") col-1 sh gr /Times-Roman-iso ff 166.67 scf sf 1350 7050 m gs 1 -1 sc 270.0 rot (cork board) col-1 sh gr /Times-Roman-iso ff 166.67 scf sf 1350 3900 m gs 1 -1 sc 270.0 rot (whiteboard) col-1 sh gr /Times-Roman-iso ff 200.00 scf sf 12300 4575 m gs"
    },
    {
      "chunk_id": 175,
      "text": "/Times-Roman-iso ff 200.00 scf sf 12300 4575 m gs 1 -1 sc 90.0 rot (21 ') col-1 sh gr /Times-Roman-iso ff 200.00 scf sf 6750 9525 m gs 1 -1 sc (36 ') col-1 sh gr /Times-Roman-iso ff 166.67 scf sf 11775 5850 m gs 1 -1 sc 270.0 rot (whiteboard) col-1"
    },
    {
      "chunk_id": 176,
      "text": "75 5850 m gs 1 -1 sc 270.0 rot (whiteboard) col-1 sh gr /Times-Roman-iso ff 166.67 scf sf 10575 2925 m gs 1 -1 sc (whiteboard) col-1 sh gr % here ends figure; $F2psEnd rs showpage %%Trailer %EOF"
    }
  ]
}