{
  "url": "http://inst.eecs.berkeley.edu/share/b/pub/grading/lib/query.pl",
  "chunks": [
    {
      "chunk_id": 1,
      "text": "# Fetch values of configuration parameters, etc. # See the file COPYING in the main distribution directory for copyright notice. $noinit = 1; unshift (@INC, '/home/ff/cs61b/grading-software/share/lib'); require \"GradingBase.pl\"; CmndLine (\"d\", 1);"
    },
    {
      "chunk_id": 2,
      "text": "b'); require \"GradingBase.pl\"; CmndLine (\"d\", 1); require \"GradingCommon.pl\"; foreach $name (@ARGV) { die \"Invalid name\" if ($name !~ /^[_A-Za-z0-9]+$/); if ($opt_d) { print (\"$name='\" . eval (\"\\$$name\") . \"';\\n\"); } else { print ((eva"
    }
  ]
}