{
  "url": "http://ptolemy.eecs.berkeley.edu/publications/papers/89/index.htm",
  "chunks": [
    {
      "chunk_id": 1,
      "text": "Ptolemy Project Papers for 1989 Skip to main content UC Berkeley EECS Dept. Quick Links People Download Publications Home Objectives Ptolemy II Other software People Sponsors Publications Conferences Presentations FAQ Download Home Presentations Copy"
    },
    {
      "chunk_id": 3,
      "text": "00 1999 1998 1997 1996 1995 1994 1993 1992 1991 1990 1989 1988 1987 1986 1985 1984 Skip to sidebar Ptolemy Project Papers for 1989 Alan Kamas and Edward A. Lee, Digital Signal Processing Experiments , Prentice-Hall, Englewood Cliffs, NJ, 1989. E. A."
    },
    {
      "chunk_id": 4,
      "text": "Prentice-Hall, Englewood Cliffs, NJ, 1989. E. A. Lee, W.-H. Ho, E. Goei, J. Bier, and S. S. Bhattacharyya, Gabriel: A Design Environment for DSP , IEEE Trans. on Acoustics, Speech, and Signal Processing , vol. 37, no. 11, pp. 1751-1762, November, 19"
    },
    {
      "chunk_id": 5,
      "text": "ing , vol. 37, no. 11, pp. 1751-1762, November, 1989. Edward A. Lee and Soonhoi Ha, Scheduling Strategies for Multiprocessor DSP , Proc. of IEEE Global Telecommunications Conference and Exhibition , vol. 2, pp. 1279-1283, November, 1989, Dallas, TX."
    },
    {
      "chunk_id": 6,
      "text": "ol. 2, pp. 1279-1283, November, 1989, Dallas, TX. G. C. Sih, P. E. Haskell, E. A. Lee, and D. G. Messerschmitt, An Overview of HDTV and Its Implications for the Broadband ISDN , Proc. of IEEE Asilomar Conf. on Signals, Systems, and Computers , vol. 2"
    },
    {
      "chunk_id": 7,
      "text": "Conf. on Signals, Systems, and Computers , vol. 2, pp. 883-887, Oct. 30 - Nov. 2, 1989, Pacific Grove, CA. Jeff Bier and Edward A. Lee, Frigg: A Simulation Environment for Multiprocessor DSP System Development , Proc. of Int. Conf. on Computer Desig"
    },
    {
      "chunk_id": 8,
      "text": "evelopment , Proc. of Int. Conf. on Computer Design , pp. 280-283, October, 1989, Boston, MA. E. A. Lee, E. Goei, H. Heine, and W. Ho, Gabriel: A Design Environment for Programmable DSPs , Proc. of IEEE Design Automation Conf. , pp. 141-146, Las Vega"
    },
    {
      "chunk_id": 9,
      "text": "EE Design Automation Conf. , pp. 141-146, Las Vegas, NV, June, 1989. E. A. Lee, E. Goei, J. Bier, and S. S. Bhattacharyya, A design tool for hardware and software for multiprocessor DSP systems , Proc. of IEEE Int. Symposium on Circuits and Systems ,"
    },
    {
      "chunk_id": 10,
      "text": ". of IEEE Int. Symposium on Circuits and Systems , vol. 2, pp. 1407-1410, Portland, OR, May, 1989. E. A. Lee, Programmable DSP Architectures, Part II , IEEE Acoustics, Speech, and Signal Processing Magazine , vol. 6, no. 1, pp. 4-14, January, 1989. C"
    },
    {
      "chunk_id": 11,
      "text": "gazine , vol. 6, no. 1, pp. 4-14, January, 1989. Contact Update Help Copyright © 1999 - UC Regents; all rights reserved."
    }
  ]
}