{
  "url": "https://wiki.eecs.berkeley.edu/accessors/Main/PtolemyIIAccessorTutorial?action=sourceblock&num=20",
  "chunks": [
    {
      "chunk_id": 1,
      "text": "bash-3.2$ bash-3.2$ cat Test.java import ptolemy.actor.lib.jjs.modules.webSocket.WebSocketHelper; import java.util.Arrays; public class Test { public static void main (String args []) { System.out.println(Arrays.toString(WebSocketHelper.s"
    },
    {
      "chunk_id": 2,
      "text": "stem.out.println(Arrays.toString(WebSocketHelper.supportedReceiveTypes())); } } bash-3.2$ javac -classpath $PTII:. Test.java bash-3.2$ $PTII/bin/ptinvoke Test [application/json, text/plain, JPG, jpg, bmp, BMP, gif, GIF, WBMP, png, PNG, jpeg, wbmp"
    },
    {
      "chunk_id": 3,
      "text": "pg, bmp, BMP, gif, GIF, WBMP, png, PNG, jpeg, wbmp, JPEG] bash-3.2$"
    }
  ]
}