{
  "url": "http://inst.eecs.berkeley.edu/share/b/pub/ps/signs/floppy.bezel.ps",
  "chunks": [
    {
      "chunk_id": 1,
      "text": "%!PS-Adobe-1.0 %%Creator: saidar.EECS.Berkeley.EDU:root (Saidar Root) %%Title: stdin (ditroff) %%CreationDate: Sat Aug 8 03:14:50 1998 %%EndComments % Start of psdit.pro -- prolog for ditroff translator % Copyright (c) 1985,1987 Adobe Systems Incorp"
    },
    {
      "chunk_id": 45,
      "text": "5(Helvetica)xf 5 f 6(Helvetica-Bold)xf 6 f 7(Courier)xf 7 f 8(Courier-Bold)xf 8 f 9(Symbol)xf 9 f 10(DIThacks)xf 10 f 10 s 1 f xi %%EndProlog %%Page: 1 1 10 s 0 xH 0 xS 1 f 8 s 3 f 10 s 576 640(/B:)N 1 f 8 s 2165(3.5\")X 2287(\\257oppy)X 2467(drive)X"
    },
    {
      "chunk_id": 47,
      "text": "(all)X 908(\\256lenames)X 1169(are)X 1262(converted)X 1529(to)X 1595(upper)X 1756(case)X 1881(on)X 1961(the)X 2055(DOS)X 2199(disk.)X 576 864(Sample)N 784(commands:)X 632 928(doscp)N 797(hello.txt)X 1025(/B:/hello.txt)X 1432(\\(copies)X 1632(\"hello.txt"
    },
    {
      "chunk_id": 48,
      "text": "25(/B:/hello.txt)X 1432(\\(copies)X 1632(\"hello.txt\")X 1912(from)X 2052(UNIX)X 2227(disk)X 2350(to)X 2416(\\257oppy\\))X 632 992(doscp)N 797(/B:/hello.txt)X 1122(hello.txt)X 1432(\\(copies)X 1632(\"hello.txt\")X 1912(from)X 2052(\\257oppy)X 2232(to)X 2298(U"
    },
    {
      "chunk_id": 51,
      "text": "4(with)X 894(PCs)X 1014(or)X 1083(Macs,)X 1253(use)X 1354(a)X 1398(DOS-formatted)X 1811(disk.)X 576 1392(Note)N 716(that)X 828(all)X 908(\\256lenames)X 1169(are)X 1262(converted)X 1529(to)X 1595(upper)X 1756(case)X 1881(on)X 1961(the)X 2055(DOS)X 2199"
    },
    {
      "chunk_id": 52,
      "text": "X 1756(case)X 1881(on)X 1961(the)X 2055(DOS)X 2199(disk.)X 576 1488(Sample)N 784(commands:)X 632 1552(doscp)N 797(hello.txt)X 1025(/B:/hello.txt)X 1432(\\(copies)X 1632(\"hello.txt\")X 1912(from)X 2052(UNIX)X 2227(disk)X 2350(to)X 2416(\\257oppy\\))X 632"
    },
    {
      "chunk_id": 56,
      "text": "formatted)X 1811(disk.)X 576 2016(Note)N 716(that)X 828(all)X 908(\\256lenames)X 1169(are)X 1262(converted)X 1529(to)X 1595(upper)X 1756(case)X 1881(on)X 1961(the)X 2055(DOS)X 2199(disk.)X 576 2112(Sample)N 784(commands:)X 632 2176(doscp)N 797(hello.t"
    },
    {
      "chunk_id": 57,
      "text": "ple)N 784(commands:)X 632 2176(doscp)N 797(hello.txt)X 1025(/B:/hello.txt)X 1432(\\(copies)X 1632(\"hello.txt\")X 1912(from)X 2052(UNIX)X 2227(disk)X 2350(to)X 2416(\\257oppy\\))X 632 2240(doscp)N 797(/B:/hello.txt)X 1122(hello.txt)X 1432(\\(copies)X 1632("
    },
    {
      "chunk_id": 61,
      "text": "enames)X 1169(are)X 1262(converted)X 1529(to)X 1595(upper)X 1756(case)X 1881(on)X 1961(the)X 2055(DOS)X 2199(disk.)X 576 2736(Sample)N 784(commands:)X 632 2800(doscp)N 797(hello.txt)X 1025(/B:/hello.txt)X 1432(\\(copies)X 1632(\"hello.txt\")X 1912(from)"
    },
    {
      "chunk_id": 62,
      "text": "xt)X 1432(\\(copies)X 1632(\"hello.txt\")X 1912(from)X 2052(UNIX)X 2227(disk)X 2350(to)X 2416(\\257oppy\\))X 632 2864(doscp)N 797(/B:/hello.txt)X 1122(hello.txt)X 1432(\\(copies)X 1632(\"hello.txt\")X 1912(from)X 2052(\\257oppy)X 2232(to)X 2298(UNIX)X 2473(di"
    },
    {
      "chunk_id": 65,
      "text": "PCs)X 1014(or)X 1083(Macs,)X 1253(use)X 1354(a)X 1398(DOS-formatted)X 1811(disk.)X 576 3264(Note)N 716(that)X 828(all)X 908(\\256lenames)X 1169(are)X 1262(converted)X 1529(to)X 1595(upper)X 1756(case)X 1881(on)X 1961(the)X 2055(DOS)X 2199(disk.)X 576"
    },
    {
      "chunk_id": 66,
      "text": "1881(on)X 1961(the)X 2055(DOS)X 2199(disk.)X 576 3360(Sample)N 784(commands:)X 632 3424(doscp)N 797(hello.txt)X 1025(/B:/hello.txt)X 1432(\\(copies)X 1632(\"hello.txt\")X 1912(from)X 2052(UNIX)X 2227(disk)X 2350(to)X 2416(\\257oppy\\))X 632 3488(doscp)N"
    },
    {
      "chunk_id": 70,
      "text": "811(disk.)X 576 3888(Note)N 716(that)X 828(all)X 908(\\256lenames)X 1169(are)X 1262(converted)X 1529(to)X 1595(upper)X 1756(case)X 1881(on)X 1961(the)X 2055(DOS)X 2199(disk.)X 576 3984(Sample)N 784(commands:)X 632 4048(doscp)N 797(hello.txt)X 1025(/B:"
    },
    {
      "chunk_id": 71,
      "text": "mands:)X 632 4048(doscp)N 797(hello.txt)X 1025(/B:/hello.txt)X 1432(\\(copies)X 1632(\"hello.txt\")X 1912(from)X 2052(UNIX)X 2227(disk)X 2350(to)X 2416(\\257oppy\\))X 632 4112(doscp)N 797(/B:/hello.txt)X 1122(hello.txt)X 1432(\\(copies)X 1632(\"hello.txt\")X"
    },
    {
      "chunk_id": 73,
      "text": "n)X 1950(the)X 2044(\\257oppy\\))X 576 4256(Please)N 755(see)X 2 f 852(/usr/pub/HP.\\257oppy.drives)X 1 f 1529(for)X 1619(more)X 1766(information.)X 10 s 576 4464(8mm)N 760(tape)X 914(drive)X 1099(on)X 1199(geri.EECS:)X 3 f 8 s 802 4544(/dev/8mm.norewin"
    },
    {
      "chunk_id": 74,
      "text": "199(geri.EECS:)X 3 f 8 s 802 4544(/dev/8mm.norewind)N 1 f 1803(\\(rewinds)X 2042(automatically\\))X 3 f 802 4608(/dev/8mm.rewind)N 1 f 1803(\\(does)X 1957(not)X 2055(rewind)X 2248(automatically\\))X 576 4688(Uses)N 716(standard)X 948(8mm)X 1096(video)X 1"
    },
    {
      "chunk_id": 75,
      "text": "688(Uses)N 716(standard)X 948(8mm)X 1096(video)X 1254(or)X 1323(data)X 1445(tapes.)X 576 4752(Read)N 723(and)X 831(write)X 978(\\256les)X 1101(with)X 1231(standard)X 1463(UNIX)X 1638('tar')X 1763(commands)X 2056(\\(type)X 2 f 2203(man)X 2329(tar)X 1 f"
    },
    {
      "chunk_id": 76,
      "text": "nds)X 2056(\\(type)X 2 f 2203(man)X 2329(tar)X 1 f 2420(for)X 2510(details\\).)X 576 4848(Sample)N 784(UNIX)X 959(commands:)X 632 4912(setenv)N 811(TAPE)X 987(/dev/8mm.norewind)X 1633(\\(assigns)X 1855(default)X 2048(drive)X 2195(name\\))X 632 4976(tar)N"
    },
    {
      "chunk_id": 77,
      "text": "efault)X 2048(drive)X 2195(name\\))X 632 4976(tar)N 715(tf)X 770($TAPE)X 1633(\\(lists)X 1774(\\256les)X 1897(on)X 1977(the)X 2071(tape\\))X 632 5040(tar)N 715(cf)X 780($TAPE)X 988(my_directory)X 1633(\\(writes)X 1826(contents)X 2055(of)X 2124(my_director"
    },
    {
      "chunk_id": 78,
      "text": "rites)X 1826(contents)X 2055(of)X 2124(my_directory)X 2484(onto)X 2614(tape\\))X 632 5104(tar)N 715(xf)X 784($TAPE)X 992(new_directory)X 1633(\\(copies)X 1833(contents)X 2062(of)X 2131(next)X 2257(tape)X 2379(\\256le)X 2477(into)X 2593(new_directory\\))X"
    },
    {
      "chunk_id": 79,
      "text": "X 2379(\\256le)X 2477(into)X 2593(new_directory\\))X 632 5168(mt)N 716(-t)X 771($TAPE)X 979(of\\257)X 1633(\\(rewinds)X 1872(and)X 1980(ejects)X 2141(tape\\))X 576 5248(Please)N 755(see)X 2 f 852(/usr/pub/tape.drives)X 1 f 1382(for)X 1472(more)X 1619(info"
    },
    {
      "chunk_id": 80,
      "text": "tape.drives)X 1 f 1382(for)X 1472(more)X 1619(information.)X 10 s 453 6112(/usr/pub/troff/\\257oppy-bezel.ms)N 1 p %%Trailer xt xs"
    }
  ]
}