{
  "url": "http://inst.eecs.berkeley.edu/share/b/pub/Instructional_Plans/Fall_2007_Enrollments.html",
  "chunks": [
    {
      "chunk_id": 1,
      "text": "EECS Course Enrollments in Multiple Classes [ ISG home page ] [ who we are ] [ send us email ] [ search ] [ FAQ ] EECS Course Enrollments in Multiple Classes A table that shows the number of students who are in more than one EECS or CS class will"
    },
    {
      "chunk_id": 2,
      "text": "who are in more than one EECS or CS class will be added here after class enrollment becomes stable in September 2007. generated by merge-data.pl (Mon Oct 16 11:55:10 US/Pacific 2006) kevinm@eecs.berkeley.edu"
    },
    {
      "chunk_id": 3,
      "text": ".berkeley.edu"
    }
  ]
}